simulateur_trafic/__init__.py
simulateur_trafic/core/__init__.py
simulateur_trafic/core/analyseur.py
simulateur_trafic/core/simulateur.py
simulateur_trafic/data/config_reseau.json
simulateur_trafic/exceptions.py
simulateur_trafic/main.py
simulateur_trafic/models/__init__.py
simulateur_trafic/models/feu_rouge.py
simulateur_trafic/models/reseau.py
simulateur_trafic/models/route.py
simulateur_trafic/models/vehicule.py
simulateur_trafic/output/__init__.py
simulateur_trafic/output/affichage.py
simulateur_trafic/output/export.py
simulateur_trafic_ahmed_hamed_2025-1.0.1.dist-info/METADATA
simulateur_trafic_ahmed_hamed_2025-1.0.1.dist-info/WHEEL
simulateur_trafic_ahmed_hamed_2025-1.0.1.dist-info/entry_points.txt
simulateur_trafic_ahmed_hamed_2025-1.0.1.dist-info/RECORD
