Metadata-Version: 2.4
Name: simulateur-trafic-ahmed-hamed-2025
Version: 1.0.1
Summary: A traffic simulation application
Author: Ahmed H.
Requires-Python: >=3.10,<3.12
Classifier: Programming Language :: Python :: 3
Classifier: Programming Language :: Python :: 3.10
Classifier: Programming Language :: Python :: 3.11
Requires-Dist: matplotlib (>=3.5.0)
Requires-Dist: numpy (>=1.21.0)
Project-URL: Homepage, https://github.com/ahmedhdhd/simulateur_trafic
Project-URL: Repository, https://github.com/ahmedhdhd/simulateur_trafic
